zope/sequencesort/__init__.py
zope/sequencesort/ssort.py
zope/sequencesort/tests/__init__.py
zope/sequencesort/tests/test_ssort.py
zope_sequencesort-6.0.dist-info/licenses/LICENSE.txt
zope_sequencesort-6.0.dist-info/METADATA
zope_sequencesort-6.0.dist-info/WHEEL
zope_sequencesort-6.0.dist-info/top_level.txt
zope_sequencesort-6.0.dist-info/RECORD
